latch_config/__init__.py
latch_config/config.py
latch_config/py.typed
latch_config-0.1.8.dist-info/LICENSE
latch_config-0.1.8.dist-info/METADATA
latch_config-0.1.8.dist-info/WHEEL
latch_config-0.1.8.dist-info/RECORD
