Metadata-Version: 2.1
Name: latch-config
Version: 0.1.8
Summary: Shared config for latch python backend services
License: CC0 1.0
Author: Max Smolin
Author-email: max@latch.bio
Requires-Python: >=3.11,<4.0
Classifier: License :: Other/Proprietary License
Classifier: Programming Language :: Python :: 3
Classifier: Programming Language :: Python :: 3.11
Classifier: Programming Language :: Python :: 3.12
